intake_pattern_catalog/__init__.py
intake_pattern_catalog/catalog.py
intake_pattern_catalog-2023.3.0.dist-info/LICENSE.md
intake_pattern_catalog-2023.3.0.dist-info/METADATA
intake_pattern_catalog-2023.3.0.dist-info/WHEEL
intake_pattern_catalog-2023.3.0.dist-info/entry_points.txt
intake_pattern_catalog-2023.3.0.dist-info/top_level.txt
intake_pattern_catalog-2023.3.0.dist-info/RECORD
