Metadata-Version: 2.1
Name: intake-pattern-catalog
Version: 2023.3.0
Summary: Intake plugin for specifying a file-path pattern which can represent a number of different entries
Author-email: Tim Hopper <tim.hopper@dtn.com>
Project-URL: repository, https://github.com/DTN-Public/intake-pattern-catalog
License-File: LICENSE.md
Requires-Dist: intake
